arabicnlp/__init__.py
arabicnlp/core.py
arabicnlp/correction.py
arabicnlp/porter.py
arabicnlp/pos_tagger.py
arabicnlp/stemmer.py
arabicnlp/data/post_lstm_march_2019_.h5
arabicnlp/data/post_ngram_march_2019.h5
arabicnlp/data/tag2index.bin
arabicnlp/data/word2index.bin
arabicnlp-0.1.7.dist-info/METADATA
arabicnlp-0.1.7.dist-info/RECORD
arabicnlp-0.1.7.dist-info/WHEEL
arabicnlp-0.1.7.dist-info/top_level.txt
