Metadata-Version: 2.1
Name: arabicnlp
Version: 0.1.7
Summary: Python package for arabic NLP
Home-page: https://github.com/adhaamehab/arabicnlp
Author: Adham Ehab
Author-email: adhaamehab7@gmail.com
License: UNKNOWN
Platform: UNKNOWN
Classifier: Development Status :: 5 - Production/Stable
Classifier: Intended Audience :: Developers
Classifier: Natural Language :: English
Classifier: License :: OSI Approved :: MIT License
Classifier: Programming Language :: Python
Classifier: Programming Language :: Python :: 2.7
Classifier: Programming Language :: Python :: 3.6
Requires-Dist: keras
Requires-Dist: tensorflow
